pip_chill/__init__.py
pip_chill/cli.py
pip_chill/pip_chill.py
pip_chill-1.0.1.dist-info/AUTHORS.rst
pip_chill-1.0.1.dist-info/LICENSE
pip_chill-1.0.1.dist-info/METADATA
pip_chill-1.0.1.dist-info/WHEEL
pip_chill-1.0.1.dist-info/entry_points.txt
pip_chill-1.0.1.dist-info/top_level.txt
pip_chill-1.0.1.dist-info/RECORD
