Metadata-Version: 2.1
Name: pip-chill
Version: 1.0.1
Summary: Like `pip freeze` but lists only the packages that are not dependencies of installed packages.
Home-page: https://github.com/rbanffy/pip-chill
Author: Ricardo Bánffy
Author-email: rbanffy@gmail.com
License: GNU General Public License v3
Keywords: pip-chill
Platform: UNKNOWN
Classifier: Development Status :: 5 - Production/Stable
Classifier: Intended Audience :: Developers
Classifier: Environment :: Console
Classifier: License :: OSI Approved :: GNU General Public License v3 or later (GPLv3+)
Classifier: Natural Language :: English
Classifier: Programming Language :: Python :: 3
Classifier: Programming Language :: Python :: 3.5
Classifier: Programming Language :: Python :: 3.6
Classifier: Programming Language :: Python :: 3.7
Classifier: Programming Language :: Python :: 3.8
Classifier: Programming Language :: Python :: 3.9
Classifier: Topic :: Software Development
